LICENSE
MANIFEST.in
README.md
pyproject.toml
setup.cfg
setup.py
ga_htmx/__init__.py
ga_htmx/apps.py
ga_htmx/check.py
ga_htmx/context_processors.py
ga_htmx/details.py
ga_htmx/middleware.py
ga_htmx/options.py
ga_htmx/render.py
ga_htmx/request.py
ga_htmx/response.py
ga_htmx/shortcuts.py
ga_htmx/types.py
ga_htmx/util.py
ga_htmx.egg-info/PKG-INFO
ga_htmx.egg-info/SOURCES.txt
ga_htmx.egg-info/dependency_links.txt
ga_htmx.egg-info/requires.txt
ga_htmx.egg-info/top_level.txt
ga_htmx/migrations/__init__.py
ga_htmx/migrations/__pycache__/__init__.cpython-311.pyc
ga_htmx/static/htmx/js/htmx.min.js
ga_htmx/static/htmx/js/htmx_ws.js
ga_htmx/templatetags/__init__.py
ga_htmx/templatetags/htmx_tags.py
ga_htmx/templatetags/__pycache__/__init__.cpython-311.pyc
ga_htmx/templatetags/__pycache__/htmx_tags.cpython-311.pyc
ga_htmx/tests/__init__.py
ga_htmx/tests/fakes.py
ga_htmx/tests/test_check.py
ga_htmx/tests/test_request.py